MANIFEST.in
requirements.txt
settings.json
setup.cfg
setup.py
supervisord.conf
bin/cesspool
cesspool/__init__.py
cesspool/pool.py
cesspool.egg-info/PKG-INFO
cesspool.egg-info/SOURCES.txt
cesspool.egg-info/dependency_links.txt
cesspool.egg-info/not-zip-safe
cesspool.egg-info/pbr.json
cesspool.egg-info/requires.txt
cesspool.egg-info/top_level.txt
cesspool/../requirements.txt
cesspool/../settings.json
cesspool/../supervisord.conf
cesspool/../www/index.html
cesspool/../www/assets/backbone.js
cesspool/../www/assets/cesspool.css
cesspool/../www/assets/cesspool.js
cesspool/../www/assets/handlebars.js
cesspool/../www/assets/jquery-ui.js
cesspool/../www/assets/jquery.min.js
cesspool/../www/assets/json2.js
cesspool/../www/assets/shmooze.js
cesspool/../www/assets/underscore.js
cesspool/../www/assets/underscore.string.min.js
cesspool/../www/assets/images/rm.png
cesspool/downloaders/__init__.py
cesspool/downloaders/downloader.py
cesspool/downloaders/torrent.py