Metadata-Version: 1.1
Name: cesspool
Version: 2.1.0
Summary: Centralized File Downloader
Home-page: https://github.com/ervanalb/cesspool
Author: Zach Banks
Author-email: zbanks@mit.edu
License: UNKNOWN
Download-URL: https://github.com/ervanalb/cesspool/tarball/2.1.0
Platform: UNKNOWN
